ecmean/__init__.py
ecmean/global_mean.py
ecmean/performance_indices.py
ecmean/climatology/EC23/pi_climatology_EC23.yml
ecmean/climatology/EC23/r360x180/climate_average_hus_ERA5_r360x180_1990-2019.nc
ecmean/climatology/EC23/r360x180/climate_average_net_sfc_NOCS_r360x180_1990-2014.nc
ecmean/climatology/EC23/r360x180/climate_average_pr_MSWEP_r360x180_1990-2019.nc
ecmean/climatology/EC23/r360x180/climate_average_psl_ERA5_r360x180_1990-2019.nc
ecmean/climatology/EC23/r360x180/climate_average_siconc_ESA-CCI-L4_r360x180_1990-2019.nc
ecmean/climatology/EC23/r360x180/climate_average_sos_ORAS5_r360x180_1990-2019.nc
ecmean/climatology/EC23/r360x180/climate_average_ta_ERA5_r360x180_1990-2019.nc
ecmean/climatology/EC23/r360x180/climate_average_tas_CRU_r360x180_1990-2019.nc
ecmean/climatology/EC23/r360x180/climate_average_tauu_ORAS5_r360x180_1990-2019.nc
ecmean/climatology/EC23/r360x180/climate_average_tauv_ORAS5_r360x180_1990-2019.nc
ecmean/climatology/EC23/r360x180/climate_average_tos_ESA-CCI-L4_r360x180_1990-2019.nc
ecmean/climatology/EC23/r360x180/climate_average_ua_ERA5_r360x180_1990-2019.nc
ecmean/climatology/EC23/r360x180/climate_average_va_ERA5_r360x180_1990-2019.nc
ecmean/climatology/EC23/r360x180/climate_variance_hus_ERA5_r360x180_1990-2019.nc
ecmean/climatology/EC23/r360x180/climate_variance_net_sfc_NOCS_r360x180_1990-2014.nc
ecmean/climatology/EC23/r360x180/climate_variance_pr_MSWEP_r360x180_1990-2019.nc
ecmean/climatology/EC23/r360x180/climate_variance_psl_ERA5_r360x180_1990-2019.nc
ecmean/climatology/EC23/r360x180/climate_variance_siconc_ESA-CCI-L4_r360x180_1990-2019.nc
ecmean/climatology/EC23/r360x180/climate_variance_sos_ORAS5_r360x180_1990-2019.nc
ecmean/climatology/EC23/r360x180/climate_variance_ta_ERA5_r360x180_1990-2019.nc
ecmean/climatology/EC23/r360x180/climate_variance_tas_CRU_r360x180_1990-2019.nc
ecmean/climatology/EC23/r360x180/climate_variance_tauu_ORAS5_r360x180_1990-2019.nc
ecmean4-0.1.14.dist-info/licenses/LICENSE
ecmean4-0.1.14.dist-info/METADATA
ecmean4-0.1.14.dist-info/WHEEL
ecmean4-0.1.14.dist-info/entry_points.txt
ecmean4-0.1.14.dist-info/top_level.txt
ecmean4-0.1.14.dist-info/RECORD
