Metadata-Version: 2.4
Name: ECmean4
Version: 0.1.14
Summary: ECmean4 Global Climate Model lightweight evaluation tool
Author-email: Paolo Davini <p.davini@isac.cnr.it>, Jost von Hardenberg <jost.hardenberg@polito.it>
Project-URL: Homepage, https://github.com/oloapinivad/ECmean4
Project-URL: Repository, https://github.com/oloapinivad/ECmean4
Project-URL: Documentation, https://ecmean4.readthedocs.io/en/latest/
Project-URL: Bug Tracker, https://github.com/oloapinivad/ECmean4/issues
Classifier: Programming Language :: Python :: 3
Classifier: Intended Audience :: Science/Research
Classifier: License :: OSI Approved :: Apache Software License
Classifier: Operating System :: OS Independent
Requires-Python: >=3.9
License-File: LICENSE
Requires-Dist: xarray
Requires-Dist: numpy
Requires-Dist: netcdf4
Requires-Dist: numba
Requires-Dist: dask
Requires-Dist: esmpy
Requires-Dist: xesmf
Requires-Dist: metpy
Requires-Dist: matplotlib
Requires-Dist: tabulate
Requires-Dist: cfgrib
Requires-Dist: seaborn
Provides-Extra: tests
Requires-Dist: coverage; extra == "tests"
Requires-Dist: coveralls; extra == "tests"
Requires-Dist: pytest; extra == "tests"
Provides-Extra: docs
Requires-Dist: sphinx<7.0; extra == "docs"
Requires-Dist: sphinx-rtd-theme; extra == "docs"
Provides-Extra: all
Requires-Dist: ECmean4[docs,tests]; extra == "all"
Dynamic: license-file
